wspd.cpython-311-x86_64-linux-musl.so
wspd-0.7.0.dist-info/RECORD
wspd-0.7.0.dist-info/WHEEL
wspd-0.7.0.dist-info/LICENSE.md
wspd-0.7.0.dist-info/METADATA
wspd-0.7.0.dist-info/top_level.txt
wspd.libs/libgcc_s-a04fdf82.so.1
wspd.libs/libstdc++-a9383cce.so.6.0.28
