Metadata-Version: 2.1
Name: wspd
Version: 0.7.0
Summary: A fast WSPD implementation.
Home-page: https://github.com/dmatijev/wspd_pip
Author: Domagoj Matijevic
Author-email: domagoj@mathos.hr
Requires-Python: >=3.7
License-File: LICENSE.md
Provides-Extra: test
Requires-Dist: pytest ; extra == 'test'
